{"description":"","displayName":"Header","methods":[],"props":{"className":{"type":{"name":"string"},"required":false,"description":"Class name of header","defaultValue":{"value":"''","computed":false}},"style":{"type":{"name":"objectOf","value":{"name":"any"}},"required":false,"description":"Css style applied to the component","defaultValue":{"value":"null","computed":false}},"tag":{"type":{"name":"string"},"required":false,"description":"Type of tag element. Can be <code>'h1'</code>, <code>'h2'</code>, <code>'h3'</code>, <code>'h4'</code>, <code>'h5'</code> and <code>'h6'</code>","defaultValue":{"value":"'h2'","computed":false}},"content":{"type":{"name":"string"},"required":false,"description":"Content of the component","defaultValue":{"value":"''","computed":false}},"customHtml":{"type":{"name":"string"},"required":false,"description":"CustomHtml of the component","defaultValue":{"value":"''","computed":false}},"id":{"type":{"name":"string"},"required":false,"description":"","defaultValue":{"value":"null","computed":false}}},"filename":"/Users/darielnoel/repositories/front10/airmodules/src/components/elements/Header/Header.jsx"}